{
  "version": "6",
  "dialect": "sqlite",
  "id": "843aa0fd-518a-4e4a-8277-0a56fc669cf3",
  "prevId": "dec809cf-5e7e-40e8-b6e2-cb28d6e03170",
  "tables": {
    "actions": {
      "name": "actions",
      "columns": {
        "id": {
          "name": "id",
          "type": "integer",
          "primaryKey": true,
          "notNull": true,
          "autoincrement": false
        },
        "type": {
          "name": "type",
          "type": "text",
          "primaryKey": false,
          "notNull": true,
          "autoincrement": false
        },
        "value": {
          "name": "value",
          "type": "text",
          "primaryKey": false,
          "notNull": false,
          "autoincrement": false
        },
        "rule_id": {
          "name": "rule_id",
          "type": "integer",
          "primaryKey": false,
          "notNull": true,
          "autoincrement": false
        }
      },
      "indexes": {
        "actions_rule_id_unique": {
          "name": "actions_rule_id_unique",
          "columns": [
            "rule_id"
          ],
          "isUnique": true
        }
      },
      "foreignKeys": {
        "actions_rule_id_rules_id_fk": {
          "name": "actions_rule_id_rules_id_fk",
          "tableFrom": "actions",
          "tableTo": "rules",
          "columnsFrom": [
            "rule_id"
          ],
          "columnsTo": [
            "id"
          ],
          "onDelete": "cascade",
          "onUpdate": "no action"
        }
      },
      "compositePrimaryKeys": {},
      "uniqueConstraints": {},
      "checkConstraints": {}
    },
    "conditions_tree": {
      "name": "conditions_tree",
      "columns": {
        "id": {
          "name": "id",
          "type": "integer",
          "primaryKey": true,
          "notNull": true,
          "autoincrement": false
        },
        "type": {
          "name": "type",
          "type": "text",
          "primaryKey": false,
          "notNull": true,
          "autoincrement": false
        },
        "display_order": {
          "name": "display_order",
          "type": "integer",
          "primaryKey": false,
          "notNull": true,
          "autoincrement": false,
          "default": 0
        },
        "rule_id": {
          "name": "rule_id",
          "type": "integer",
          "primaryKey": false,
          "notNull": true,
          "autoincrement": false
        },
        "parent_group_id": {
          "name": "parent_group_id",
          "type": "integer",
          "primaryKey": false,
          "notNull": false,
          "autoincrement": false
        },
        "operator": {
          "name": "operator",
          "type": "text",
          "primaryKey": false,
          "notNull": false,
          "autoincrement": false
        },
        "field": {
          "name": "field",
          "type": "text",
          "primaryKey": false,
          "notNull": false,
          "autoincrement": false
        },
        "field_operator": {
          "name": "field_operator",
          "type": "text",
          "primaryKey": false,
          "notNull": false,
          "autoincrement": false
        },
        "value": {
          "name": "value",
          "type": "text",
          "primaryKey": false,
          "notNull": false,
          "autoincrement": false
        },
        "value2": {
          "name": "value2",
          "type": "text",
          "primaryKey": false,
          "notNull": false,
          "autoincrement": false
        }
      },
      "indexes": {},
      "foreignKeys": {
        "conditions_tree_rule_id_rules_id_fk": {
          "name": "conditions_tree_rule_id_rules_id_fk",
          "tableFrom": "conditions_tree",
          "tableTo": "rules",
          "columnsFrom": [
            "rule_id"
          ],
          "columnsTo": [
            "id"
          ],
          "onDelete": "cascade",
          "onUpdate": "no action"
        },
        "conditions_tree_parent_group_id_conditions_tree_id_fk": {
          "name": "conditions_tree_parent_group_id_conditions_tree_id_fk",
          "tableFrom": "conditions_tree",
          "tableTo": "conditions_tree",
          "columnsFrom": [
            "parent_group_id"
          ],
          "columnsTo": [
            "id"
          ],
          "onDelete": "cascade",
          "onUpdate": "no action"
        }
      },
      "compositePrimaryKeys": {},
      "uniqueConstraints": {},
      "checkConstraints": {}
    },
    "folders": {
      "name": "folders",
      "columns": {
        "id": {
          "name": "id",
          "type": "integer",
          "primaryKey": true,
          "notNull": true,
          "autoincrement": false
        },
        "name": {
          "name": "name",
          "type": "text",
          "primaryKey": false,
          "notNull": true,
          "autoincrement": false
        },
        "full_path": {
          "name": "full_path",
          "type": "text(150)",
          "primaryKey": false,
          "notNull": true,
          "autoincrement": false
        }
      },
      "indexes": {
        "folders_full_path_unique": {
          "name": "folders_full_path_unique",
          "columns": [
            "full_path"
          ],
          "isUnique": true
        }
      },
      "foreignKeys": {},
      "compositePrimaryKeys": {},
      "uniqueConstraints": {},
      "checkConstraints": {}
    },
    "profiles": {
      "name": "profiles",
      "columns": {
        "id": {
          "name": "id",
          "type": "integer",
          "primaryKey": true,
          "notNull": true,
          "autoincrement": false
        },
        "name": {
          "name": "name",
          "type": "text",
          "primaryKey": false,
          "notNull": true,
          "autoincrement": false
        },
        "description": {
          "name": "description",
          "type": "text(150)",
          "primaryKey": false,
          "notNull": false,
          "autoincrement": false
        },
        "icon_id": {
          "name": "icon_id",
          "type": "text",
          "primaryKey": false,
          "notNull": true,
          "autoincrement": false,
          "default": "'fluent-emoji:file-folder'"
        },
        "is_active": {
          "name": "is_active",
          "type": "integer",
          "primaryKey": false,
          "notNull": true,
          "autoincrement": false,
          "default": true
        },
        "is_system": {
          "name": "is_system",
          "type": "integer",
          "primaryKey": false,
          "notNull": true,
          "autoincrement": false,
          "default": false
        }
      },
      "indexes": {
        "profiles_name_unique": {
          "name": "profiles_name_unique",
          "columns": [
            "name"
          ],
          "isUnique": true
        }
      },
      "foreignKeys": {},
      "compositePrimaryKeys": {},
      "uniqueConstraints": {},
      "checkConstraints": {}
    },
    "profile_folders": {
      "name": "profile_folders",
      "columns": {
        "profile_id": {
          "name": "profile_id",
          "type": "integer",
          "primaryKey": false,
          "notNull": true,
          "autoincrement": false
        },
        "folder_id": {
          "name": "folder_id",
          "type": "integer",
          "primaryKey": false,
          "notNull": true,
          "autoincrement": false
        }
      },
      "indexes": {},
      "foreignKeys": {
        "profile_folders_profile_id_profiles_id_fk": {
          "name": "profile_folders_profile_id_profiles_id_fk",
          "tableFrom": "profile_folders",
          "tableTo": "profiles",
          "columnsFrom": [
            "profile_id"
          ],
          "columnsTo": [
            "id"
          ],
          "onDelete": "cascade",
          "onUpdate": "no action"
        },
        "profile_folders_folder_id_folders_id_fk": {
          "name": "profile_folders_folder_id_folders_id_fk",
          "tableFrom": "profile_folders",
          "tableTo": "folders",
          "columnsFrom": [
            "folder_id"
          ],
          "columnsTo": [
            "id"
          ],
          "onDelete": "cascade",
          "onUpdate": "no action"
        }
      },
      "compositePrimaryKeys": {
        "profile_folders_profile_id_folder_id_pk": {
          "columns": [
            "profile_id",
            "folder_id"
          ],
          "name": "profile_folders_profile_id_folder_id_pk"
        }
      },
      "uniqueConstraints": {},
      "checkConstraints": {}
    },
    "profile_rules": {
      "name": "profile_rules",
      "columns": {
        "profile_id": {
          "name": "profile_id",
          "type": "integer",
          "primaryKey": false,
          "notNull": true,
          "autoincrement": false
        },
        "rule_id": {
          "name": "rule_id",
          "type": "integer",
          "primaryKey": false,
          "notNull": true,
          "autoincrement": false
        }
      },
      "indexes": {},
      "foreignKeys": {
        "profile_rules_profile_id_profiles_id_fk": {
          "name": "profile_rules_profile_id_profiles_id_fk",
          "tableFrom": "profile_rules",
          "tableTo": "profiles",
          "columnsFrom": [
            "profile_id"
          ],
          "columnsTo": [
            "id"
          ],
          "onDelete": "cascade",
          "onUpdate": "no action"
        },
        "profile_rules_rule_id_rules_id_fk": {
          "name": "profile_rules_rule_id_rules_id_fk",
          "tableFrom": "profile_rules",
          "tableTo": "rules",
          "columnsFrom": [
            "rule_id"
          ],
          "columnsTo": [
            "id"
          ],
          "onDelete": "cascade",
          "onUpdate": "no action"
        }
      },
      "compositePrimaryKeys": {
        "profile_rules_profile_id_rule_id_pk": {
          "columns": [
            "profile_id",
            "rule_id"
          ],
          "name": "profile_rules_profile_id_rule_id_pk"
        }
      },
      "uniqueConstraints": {},
      "checkConstraints": {}
    },
    "rules": {
      "name": "rules",
      "columns": {
        "id": {
          "name": "id",
          "type": "integer",
          "primaryKey": true,
          "notNull": true,
          "autoincrement": false
        },
        "name": {
          "name": "name",
          "type": "text",
          "primaryKey": false,
          "notNull": true,
          "autoincrement": false
        },
        "description": {
          "name": "description",
          "type": "text(255)",
          "primaryKey": false,
          "notNull": false,
          "autoincrement": false
        },
        "is_system": {
          "name": "is_system",
          "type": "integer",
          "primaryKey": false,
          "notNull": true,
          "autoincrement": false,
          "default": false
        },
        "is_active": {
          "name": "is_active",
          "type": "integer",
          "primaryKey": false,
          "notNull": true,
          "autoincrement": false,
          "default": true
        }
      },
      "indexes": {
        "rules_name_unique": {
          "name": "rules_name_unique",
          "columns": [
            "name"
          ],
          "isUnique": true
        }
      },
      "foreignKeys": {},
      "compositePrimaryKeys": {},
      "uniqueConstraints": {},
      "checkConstraints": {}
    },
    "settings": {
      "name": "settings",
      "columns": {
        "id": {
          "name": "id",
          "type": "integer",
          "primaryKey": true,
          "notNull": true,
          "autoincrement": false
        },
        "title": {
          "name": "title",
          "type": "text",
          "primaryKey": false,
          "notNull": true,
          "autoincrement": false
        },
        "description": {
          "name": "description",
          "type": "text",
          "primaryKey": false,
          "notNull": false,
          "autoincrement": false
        },
        "category": {
          "name": "category",
          "type": "text",
          "primaryKey": false,
          "notNull": false,
          "autoincrement": false
        },
        "is_active": {
          "name": "is_active",
          "type": "integer",
          "primaryKey": false,
          "notNull": true,
          "autoincrement": false,
          "default": true
        }
      },
      "indexes": {},
      "foreignKeys": {},
      "compositePrimaryKeys": {},
      "uniqueConstraints": {},
      "checkConstraints": {}
    },
    "affected_files": {
      "name": "affected_files",
      "columns": {
        "id": {
          "name": "id",
          "type": "integer",
          "primaryKey": true,
          "notNull": true,
          "autoincrement": false
        },
        "log_id": {
          "name": "log_id",
          "type": "integer",
          "primaryKey": false,
          "notNull": true,
          "autoincrement": false
        },
        "current_value": {
          "name": "current_value",
          "type": "text",
          "primaryKey": false,
          "notNull": true,
          "autoincrement": false
        },
        "new_value": {
          "name": "new_value",
          "type": "text",
          "primaryKey": false,
          "notNull": false,
          "autoincrement": false
        }
      },
      "indexes": {},
      "foreignKeys": {
        "affected_files_log_id_organization_logs_id_fk": {
          "name": "affected_files_log_id_organization_logs_id_fk",
          "tableFrom": "affected_files",
          "tableTo": "organization_logs",
          "columnsFrom": [
            "log_id"
          ],
          "columnsTo": [
            "id"
          ],
          "onDelete": "cascade",
          "onUpdate": "no action"
        }
      },
      "compositePrimaryKeys": {},
      "uniqueConstraints": {},
      "checkConstraints": {}
    },
    "organization_logs": {
      "name": "organization_logs",
      "columns": {
        "id": {
          "name": "id",
          "type": "integer",
          "primaryKey": true,
          "notNull": true,
          "autoincrement": false
        },
        "type": {
          "name": "type",
          "type": "text",
          "primaryKey": false,
          "notNull": true,
          "autoincrement": false
        },
        "metadata": {
          "name": "metadata",
          "type": "text",
          "primaryKey": false,
          "notNull": true,
          "autoincrement": false
        },
        "created_at": {
          "name": "created_at",
          "type": "integer",
          "primaryKey": false,
          "notNull": true,
          "autoincrement": false,
          "default": "(strftime('%s', 'now') * 1000)"
        }
      },
      "indexes": {},
      "foreignKeys": {},
      "compositePrimaryKeys": {},
      "uniqueConstraints": {},
      "checkConstraints": {}
    }
  },
  "views": {},
  "enums": {},
  "_meta": {
    "schemas": {},
    "tables": {},
    "columns": {
      "\"affected_files\".\"path\"": "\"affected_files\".\"current_value\""
    }
  },
  "internal": {
    "indexes": {}
  }
}